{
    "Height": Short(16),
    "Metadata": Compound({
        "WEOffsetX": Int(-17),
        "WEOffsetY": Int(0),
        "WEOffsetZ": Int(-8)
    }),
    "DataVersion": Int(2584),
    "Width": Short(19),
    "Palette": Compound({
        "minecraft:potatoes[age=7]": Int(18),
        "minecraft:andesite_stairs[facing=west,half=bottom,shape=straight,waterlogged=false]": Int(37),
        "minecraft:spruce_door[facing=east,half=upper,hinge=left,open=false,powered=false]": Int(75),
        "minecraft:spruce_trapdoor[facing=north,half=bottom,open=false,powered=false,waterlogged=false]": Int(78),
        "minecraft:spruce_wall_sign[facing=south,waterlogged=false]": Int(58),
        "minecraft:birch_leaves[distance=2,persistent=true]": Int(66),
        "minecraft:chest[facing=north,type=single,waterlogged=false]": Int(61),
        "minecraft:birch_leaves[distance=7,persistent=true]": Int(79),
        "minecraft:potatoes[age=3]": Int(29),
        "minecraft:brown_carpet": Int(72),
        "minecraft:spruce_button[face=wall,facing=south,powered=false]": Int(113),
        "minecraft:barrel[facing=north,open=false]": Int(62),
        "minecraft:grass": Int(30),
        "minecraft:birch_slab[type=double,waterlogged=false]": Int(110),
        "minecraft:spruce_leaves[distance=3,persistent=false]": Int(104),
        "minecraft:barrel[facing=up,open=false]": Int(63),
        "minecraft:spruce_wood[axis=y]": Int(114),
        "minecraft:mossy_cobblestone": Int(36),
        "minecraft:podzol[snowy=false]": Int(6),
        "minecraft:spruce_stairs[facing=south,half=top,shape=straight,waterlogged=false]": Int(96),
        "minecraft:stone_stairs[facing=east,half=bottom,shape=straight,waterlogged=false]": Int(82),
        "minecraft:birch_planks": Int(45),
        "minecraft:spruce_slab[type=top,waterlogged=false]": Int(26),
        "minecraft:birch_stairs[facing=north,half=top,shape=outer_left,waterlogged=false]": Int(107),
        "minecraft:spruce_door[facing=east,half=lower,hinge=left,open=false,powered=false]": Int(60),
        "minecraft:potatoes[age=2]": Int(24),
        "minecraft:oak_slab[type=top,waterlogged=false]": Int(54),
        "minecraft:stone": Int(0),
        "minecraft:spruce_trapdoor[facing=east,half=bottom,open=true,powered=false,waterlogged=false]": Int(56),
        "minecraft:spruce_leaves[distance=5,persistent=false]": Int(103),
        "minecraft:stripped_spruce_wood[axis=y]": Int(21),
        "minecraft:spruce_trapdoor[facing=east,half=bottom,open=false,powered=false,waterlogged=false]": Int(99),
        "minecraft:brown_stained_glass_pane[east=true,north=false,south=false,waterlogged=false,west=true]": Int(76),
        "minecraft:andesite_stairs[facing=north,half=bottom,shape=straight,waterlogged=false]": Int(83),
        "minecraft:oak_stairs[facing=north,half=top,shape=straight,waterlogged=false]": Int(49),
        "minecraft:acacia_trapdoor[facing=south,half=bottom,open=true,powered=false,waterlogged=false]": Int(42),
        "minecraft:potatoes[age=5]": Int(33),
        "minecraft:gravel": Int(4),
        "minecraft:spruce_slab[type=double,waterlogged=false]": Int(25),
        "minecraft:birch_stairs[facing=east,half=top,shape=straight,waterlogged=false]": Int(85),
        "minecraft:spruce_stairs[facing=east,half=bottom,shape=straight,waterlogged=false]": Int(28),
        "minecraft:spruce_stairs[facing=south,half=bottom,shape=inner_right,waterlogged=false]": Int(109),
        "minecraft:lantern[hanging=true,waterlogged=false]": Int(86),
        "minecraft:spruce_slab[type=bottom,waterlogged=false]": Int(7),
        "minecraft:coarse_dirt": Int(20),
        "minecraft:flower_pot": Int(73),
        "minecraft:spruce_stairs[facing=west,half=bottom,shape=straight,waterlogged=false]": Int(27),
        "minecraft:spruce_stairs[facing=north,half=bottom,shape=straight,waterlogged=false]": Int(65),
        "minecraft:spruce_trapdoor[facing=south,half=top,open=false,powered=false,waterlogged=false]": Int(32),
        "minecraft:chest[facing=west,type=single,waterlogged=false]": Int(51),
        "minecraft:dark_oak_slab[type=bottom,waterlogged=false]": Int(55),
        "minecraft:andesite_stairs[facing=south,half=bottom,shape=straight,waterlogged=false]": Int(80),
        "minecraft:oak_stairs[facing=south,half=top,shape=straight,waterlogged=false]": Int(57),
        "minecraft:green_bed[facing=east,occupied=false,part=head]": Int(44),
        "minecraft:spruce_stairs[facing=east,half=top,shape=straight,waterlogged=false]": Int(92),
        "minecraft:air": Int(16),
        "minecraft:tall_grass[half=upper]": Int(53),
        "minecraft:tall_grass[half=lower]": Int(23),
        "minecraft:grass_block[snowy=false]": Int(5),
        "minecraft:andesite": Int(2),
        "minecraft:spruce_trapdoor[facing=east,half=top,open=false,powered=false,waterlogged=false]": Int(89),
        "minecraft:stripped_spruce_wood[axis=x]": Int(100),
        "minecraft:spruce_log[axis=z]": Int(95),
        "minecraft:spruce_log[axis=x]": Int(93),
        "minecraft:light_gray_carpet": Int(47),
        "minecraft:stone_slab[type=bottom,waterlogged=false]": Int(22),
        "minecraft:stone_slab[type=double,waterlogged=false]": Int(19),
        "minecraft:stripped_spruce_wood[axis=z]": Int(14),
        "minecraft:spruce_wall_sign[facing=north,waterlogged=false]": Int(50),
        "minecraft:spruce_leaves[distance=4,persistent=false]": Int(102),
        "minecraft:cobblestone_stairs[facing=north,half=bottom,shape=straight,waterlogged=false]": Int(15),
        "minecraft:cobblestone": Int(1),
        "minecraft:stone_slab[type=top,waterlogged=false]": Int(38),
        "minecraft:birch_stairs[facing=west,half=top,shape=straight,waterlogged=false]": Int(87),
        "minecraft:spruce_stairs[facing=west,half=bottom,shape=inner_right,waterlogged=false]": Int(98),
        "minecraft:birch_stairs[facing=north,half=top,shape=straight,waterlogged=false]": Int(90),
        "minecraft:potatoes[age=4]": Int(11),
        "minecraft:campfire[facing=west,lit=false,signal_fire=false,waterlogged=false]": Int(117),
        "minecraft:scaffolding[bottom=false,distance=0,waterlogged=false]": Int(48),
        "minecraft:birch_leaves[distance=3,persistent=true]": Int(67),
        "minecraft:stone_stairs[facing=north,half=bottom,shape=straight,waterlogged=false]": Int(41),
        "minecraft:birch_leaves[distance=1,persistent=true]": Int(34),
        "minecraft:birch_stairs[facing=east,half=bottom,shape=straight,waterlogged=false]": Int(46),
        "minecraft:spruce_leaves[distance=1,persistent=false]": Int(106),
        "minecraft:spruce_log[axis=y]": Int(8),
        "minecraft:stripped_birch_wood[axis=y]": Int(40),
        "minecraft:spruce_fence[east=false,north=false,south=false,waterlogged=false,west=false]": Int(77),
        "minecraft:stripped_birch_log[axis=x]": Int(68),
        "minecraft:spruce_stairs[facing=north,half=top,shape=straight,waterlogged=false]": Int(94),
        "minecraft:stripped_birch_log[axis=y]": Int(52),
        "minecraft:birch_stairs[facing=south,half=top,shape=straight,waterlogged=false]": Int(112),
        "minecraft:potatoes[age=6]": Int(10),
        "minecraft:spruce_trapdoor[facing=west,half=bottom,open=true,powered=false,waterlogged=false]": Int(116),
        "minecraft:composter[level=5]": Int(31),
        "minecraft:spruce_trapdoor[facing=north,half=top,open=false,powered=false,waterlogged=false]": Int(81),
        "minecraft:spruce_leaves[distance=2,persistent=false]": Int(105),
        "minecraft:spruce_planks": Int(13),
        "minecraft:spruce_trapdoor[facing=south,half=bottom,open=true,powered=false,waterlogged=false]": Int(118),
        "minecraft:campfire[facing=north,lit=false,signal_fire=false,waterlogged=false]": Int(39),
        "minecraft:birch_slab[type=top,waterlogged=false]": Int(111),
        "minecraft:stone_stairs[facing=north,half=top,shape=straight,waterlogged=false]": Int(84),
        "minecraft:spruce_leaves[distance=6,persistent=false]": Int(101),
        "minecraft:andesite_stairs[facing=north,half=top,shape=straight,waterlogged=false]": Int(70),
        "minecraft:spruce_door[facing=west,half=lower,hinge=right,open=false,powered=false]": Int(59),
        "minecraft:spruce_stairs[facing=south,half=bottom,shape=straight,waterlogged=false]": Int(35),
        "minecraft:dirt": Int(3),
        "minecraft:spruce_trapdoor[facing=west,half=top,open=false,powered=false,waterlogged=false]": Int(88),
        "minecraft:birch_stairs[facing=north,half=bottom,shape=straight,waterlogged=false]": Int(64),
        "minecraft:potatoes[age=0]": Int(17),
        "minecraft:birch_stairs[facing=north,half=top,shape=outer_right,waterlogged=false]": Int(108),
        "minecraft:cobblestone_stairs[facing=north,half=top,shape=straight,waterlogged=false]": Int(69),
        "minecraft:potatoes[age=1]": Int(9),
        "minecraft:brown_stained_glass_pane[east=false,north=true,south=true,waterlogged=false,west=false]": Int(71),
        "minecraft:green_bed[facing=east,occupied=false,part=foot]": Int(43),
        "minecraft:spruce_stairs[facing=west,half=top,shape=straight,waterlogged=false]": Int(91),
        "minecraft:spruce_fence[east=false,north=true,south=true,waterlogged=false,west=false]": Int(97),
        "minecraft:spruce_trapdoor[facing=north,half=bottom,open=true,powered=false,waterlogged=false]": Int(115),
        "minecraft:spruce_door[facing=west,half=upper,hinge=right,open=false,powered=false]": Int(74),
        "minecraft:andesite_stairs[facing=east,half=bottom,shape=straight,waterlogged=false]": Int(12)
    }),
    "Length": Short(14),
    "Version": Int(2),
    "BlockEntities": List([Compound({
            "Id": String("minecraft:campfire"),
            "Pos": IntArray(IntArray { data: [
                    12,
                    1,
                    2
                ]
            }),
            "CookingTotalTimes": IntArray(IntArray { data: [
                    0,
                    0,
                    0,
                    0
                ]
            }),
            "Items": List([]),
            "CookingTimes": IntArray(IntArray { data: [
                    0,
                    0,
                    0,
                    0
                ]
            })
        }), Compound({
            "Id": String("minecraft:bed"),
            "Pos": IntArray(IntArray { data: [
                    14,
                    1,
                    3
                ]
            })
        }), Compound({
            "Id": String("minecraft:bed"),
            "Pos": IntArray(IntArray { data: [
                    15,
                    1,
                    3
                ]
            })
        }), Compound({
            "Text2": String("{\"text\":\"\"}"),
            "Id": String("minecraft:sign"),
            "Text4": String("{\"text\":\"\"}"),
            "Color": String("black"),
            "Text1": String("{\"text\":\"\"}"),
            "Pos": IntArray(IntArray { data: [
                    12,
                    1,
                    5
                ]
            }),
            "Text3": String("{\"text\":\"\"}")
        }), Compound({
            "Pos": IntArray(IntArray { data: [
                    15,
                    1,
                    5
                ]
            }),
            "Id": String("minecraft:chest"),
            "Items": List([])
        }), Compound({
            "Color": String("black"),
            "Text3": String("{\"text\":\"\"}"),
            "Text2": String("{\"text\":\"\"}"),
            "Pos": IntArray(IntArray { data: [
                    12,
                    1,
                    7
                ]
            }),
            "Id": String("minecraft:sign"),
            "Text4": String("{\"text\":\"\"}"),
            "Text1": String("{\"text\":\"\"}")
        }), Compound({
            "Pos": IntArray(IntArray { data: [
                    11,
                    1,
                    9
                ]
            }),
            "Items": List([]),
            "Id": String("minecraft:chest")
        }), Compound({
            "Items": List([]),
            "Id": String("minecraft:barrel"),
            "Pos": IntArray(IntArray { data: [
                    12,
                    1,
                    9
                ]
            })
        }), Compound({
            "Items": List([]),
            "Id": String("minecraft:barrel"),
            "Pos": IntArray(IntArray { data: [
                    13,
                    1,
                    9
                ]
            })
        }), Compound({
            "Id": String("minecraft:barrel"),
            "Pos": IntArray(IntArray { data: [
                    16,
                    5,
                    3
                ]
            }),
            "Items": List([])
        }), Compound({
            "Items": List([]),
            "Pos": IntArray(IntArray { data: [
                    16,
                    5,
                    5
                ]
            }),
            "Id": String("minecraft:barrel")
        }), Compound({
            "Items": List([]),
            "Pos": IntArray(IntArray { data: [
                    11,
                    5,
                    10
                ]
            }),
            "Id": String("minecraft:barrel")
        }), Compound({
            "Id": String("minecraft:barrel"),
            "Pos": IntArray(IntArray { data: [
                    13,
                    5,
                    10
                ]
            }),
            "Items": List([])
        }), Compound({
            "Pos": IntArray(IntArray { data: [
                    12,
                    11,
                    2
                ]
            }),
            "CookingTotalTimes": IntArray(IntArray { data: [
                    0,
                    0,
                    0,
                    0
                ]
            }),
            "CookingTimes": IntArray(IntArray { data: [
                    0,
                    0,
                    0,
                    0
                ]
            }),
            "Id": String("minecraft:campfire"),
            "Items": List([])
        })
    ]),
    "Offset": IntArray(IntArray { data: [
            144,
            72,
            16
        ]
    }),
    "PaletteMax": Int(119),
    "BlockData": ByteArray(ByteArray { data: [
            0,
            0,
            0,
            0,
            0,
            1,
            1,
            2,
            3,
            0,
            1,
            2,
            1,
            1,
            4,
            5,
            5,
            5,
            2,
            0,
            0,
            0,
            0,
            0,
            6,
            3,
            3,
            2,
            5,
            6,
            1,
            1,
            1,
            6,
            5,
            3,
            5,
            5,
            0,
            0,
            6,
            4,
            4,
            6,
            0,
            7,
            8,
            8,
            8,
            1,
            1,
            1,
            8,
            1,
            8,
            8,
            6,
            0,
            2,
            2,
            6,
            6,
            9,
            10,
            11,
            9,
            12,
            1,
            13,
            13,
            13,
            13,
            14,
            2,
            15,
            16,
            0,
            6,
            6,
            1,
            16,
            17,
            18,
            18,
            10,
            10,
            2,
            14,
            13,
            13,
            13,
            13,
            19,
            16,
            16,
            4,
            20,
            2,
            16,
            16,
            11,
            16,
            11,
            16,
            9,
            1,
            13,
            13,
            21,
            13,
            13,
            1,
            22,
            23,
            20,
            20,
            8,
            16,
            24,
            9,
            9,
            16,
            16,
            22,
            8,
            14,
            13,
            13,
            8,
            1,
            8,
            8,
            16,
            20,
            25,
            16,
            16,
            17,
            16,
            16,
            16,
            16,
            8,
            1,
            13,
            13,
            13,
            13,
            26,
            27,
            16,
            16,
            5,
            7,
            11,
            16,
            16,
            16,
            16,
            16,
            16,
            28,
            13,
            13,
            13,
            21,
            13,
            26,
            27,
            16,
            16,
            8,
            18,
            24,
            16,
            16,
            10,
            16,
            23,
            16,
            8,
            1,
            14,
            13,
            13,
            13,
            21,
            27,
            16,
            16,
            25,
            29,
            17,
            17,
            11,
            10,
            30,
            16,
            31,
            7,
            8,
            1,
            1,
            1,
            8,
            32,
            8,
            30,
            16,
            16,
            7,
            16,
            10,
            33,
            16,
            30,
            7,
            8,
            5,
            3,
            5,
            5,
            22,
            8,
            34,
            30,
            23,
            30,
            26,
            8,
            25,
            7,
            7,
            8,
            35,
            5,
            0,
            0,
            6,
            6,
            5,
            6,
            34,
            16,
            30,
            30,
            30,
            16,
            16,
            16,
            16,
            6,
            5,
            5,
            0,
            1,
            6,
            6,
            3,
            6,
            6,
            6,
            16,
            16,
            30,
            23,
            3,
            3,
            3,
            6,
            20,
            36,
            0,
            4,
            20,
            0,
            36,
            0,
            0,
            0,
            16,
            16,
            16,
            30,
            16,
            6,
            3,
            6,
            2,
            0,
            20,
            20,
            20,
            2,
            16,
            35,
            1,
            0,
            1,
            37,
            16,
            35,
            30,
            30,
            6,
            6,
            6,
            0,
            0,
            38,
            2,
            26,
            8,
            28,
            8,
            1,
            39,
            1,
            8,
            40,
            8,
            27,
            16,
            6,
            0,
            36,
            6,
            1,
            16,
            16,
            16,
            16,
            16,
            40,
            41,
            42,
            15,
            43,
            44,
            45,
            16,
            16,
            0,
            6,
            6,
            6,
            16,
            16,
            16,
            16,
            16,
            16,
            46,
            16,
            47,
            47,
            16,
            48,
            45,
            16,
            16,
            0,
            20,
            4,
            16,
            16,
            16,
            16,
            16,
            16,
            16,
            40,
            49,
            50,
            47,
            47,
            51,
            52,
            16,
            53,
            20,
            16,
            8,
            16,
            16,
            16,
            16,
            16,
            16,
            16,
            8,
            54,
            55,
            56,
            8,
            52,
            8,
            27,
            16,
            16,
            25,
            16,
            16,
            16,
            16,
            16,
            16,
            16,
            28,
            40,
            57,
            58,
            47,
            45,
            16,
            16,
            16,
            16,
            16,
            7,
            16,
            16,
            16,
            16,
            16,
            16,
            16,
            16,
            59,
            16,
            47,
            47,
            60,
            16,
            16,
            16,
            16,
            8,
            16,
            16,
            16,
            16,
            16,
            16,
            53,
            16,
            28,
            45,
            61,
            62,
            63,
            52,
            16,
            16,
            16,
            16,
            7,
            16,
            16,
            16,
            16,
            16,
            16,
            16,
            16,
            7,
            8,
            45,
            64,
            40,
            8,
            16,
            8,
            16,
            16,
            16,
            7,
            16,
            16,
            16,
            16,
            16,
            7,
            8,
            16,
            65,
            16,
            66,
            34,
            65,
            16,
            16,
            53,
            16,
            16,
            8,
            7,
            7,
            7,
            8,
            7,
            16,
            16,
            16,
            16,
            16,
            67,
            16,
            16,
            16,
            16,
            16,
            16,
            16,
            16,
            16,
            16,
            16,
            16,
            16,
            16,
            3,
            6,
            6,
            5,
            16,
            16,
            16,
            16,
            16,
            16,
            53,
            3,
            6,
            6,
            6,
            20,
            2,
            4,
            2,
            20,
            16,
            16,
            16,
            1,
            16,
            16,
            16,
            16,
            16,
            16,
            6,
            6,
            6,
            2,
            4,
            20,
            20,
            16,
            22,
            16,
            16,
            1,
            1,
            0,
            16,
            16,
            16,
            16,
            16,
            6,
            6,
            6,
            0,
            2,
            6,
            16,
            16,
            8,
            16,
            8,
            1,
            16,
            2,
            8,
            68,
            8,
            16,
            16,
            6,
            0,
            36,
            6,
            6,
            16,
            16,
            16,
            16,
            16,
            45,
            69,
            16,
            70,
            16,
            16,
            52,
            16,
            16,
            1,
            6,
            6,
            16,
            16,
            16,
            16,
            16,
            16,
            16,
            71,
            16,
            16,
            16,
            16,
            72,
            71,
            16,
            16,
            16,
            16,
            16,
            16,
            16,
            16,
            16,
            16,
            16,
            16,
            40,
            73,
            16,
            16,
            16,
            16,
            52,
            16,
            16,
            16,
            16,
            28,
            16,
            16,
            16,
            16,
            16,
            16,
            16,
            8,
            16,
            16,
            56,
            8,
            45,
            8,
            16,
            16,
            16,
            16,
            16,
            16,
            16,
            16,
            16,
            16,
            16,
            16,
            45,
            16,
            16,
            16,
            52,
            16,
            16,
            16,
            16,
            16,
            16,
            16,
            16,
            16,
            16,
            16,
            16,
            16,
            16,
            74,
            16,
            16,
            16,
            75,
            16,
            16,
            16,
            16,
            7,
            16,
            16,
            16,
            16,
            16,
            16,
            16,
            16,
            16,
            40,
            16,
            16,
            16,
            45,
            16,
            16,
            16,
            16,
            16,
            16,
            16,
            16,
            16,
            16,
            16,
            16,
            16,
            16,
            8,
            40,
            76,
            45,
            8,
            16,
            77,
            16,
            16,
            16,
            16,
            16,
            16,
            16,
            16,
            16,
            16,
            7,
            16,
            16,
            16,
            16,
            66,
            16,
            16,
            16,
            16,
            16,
            16,
            78,
            16,
            16,
            16,
            35,
            16,
            16,
            16,
            16,
            16,
            16,
            16,
            16,
            16,
            16,
            16,
            16,
            16,
            16,
            16,
            16,
            16,
            16,
            16,
            16,
            16,
            8,
            16,
            16,
            79,
            16,
            16,
            16,
            16,
            16,
            16,
            16,
            3,
            6,
            6,
            6,
            20,
            2,
            4,
            16,
            16,
            16,
            16,
            16,
            80,
            16,
            16,
            16,
            16,
            16,
            16,
            6,
            6,
            6,
            4,
            2,
            20,
            16,
            16,
            16,
            16,
            81,
            82,
            1,
            1,
            81,
            16,
            81,
            16,
            16,
            6,
            6,
            6,
            0,
            4,
            16,
            16,
            16,
            16,
            81,
            8,
            0,
            16,
            1,
            8,
            45,
            8,
            16,
            16,
            6,
            4,
            16,
            16,
            16,
            16,
            16,
            16,
            16,
            16,
            40,
            83,
            84,
            83,
            32,
            16,
            52,
            16,
            16,
            0,
            6,
            16,
            16,
            16,
            16,
            16,
            16,
            16,
            16,
            85,
            16,
            16,
            16,
            86,
            16,
            87,
            16,
            16,
            16,
            16,
            16,
            16,
            16,
            16,
            16,
            16,
            16,
            16,
            45,
            16,
            16,
            16,
            81,
            16,
            52,
            16,
            16,
            16,
            16,
            16,
            16,
            16,
            16,
            16,
            16,
            16,
            88,
            8,
            89,
            16,
            81,
            8,
            52,
            8,
            16,
            16,
            16,
            16,
            16,
            16,
            16,
            16,
            16,
            16,
            16,
            16,
            40,
            16,
            16,
            16,
            52,
            89,
            16,
            16,
            16,
            16,
            16,
            16,
            16,
            16,
            16,
            16,
            16,
            16,
            16,
            85,
            16,
            86,
            16,
            87,
            16,
            16,
            16,
            16,
            16,
            16,
            16,
            16,
            16,
            16,
            16,
            16,
            16,
            16,
            45,
            16,
            16,
            16,
            52,
            16,
            16,
            16,
            16,
            16,
            16,
            16,
            16,
            16,
            16,
            16,
            16,
            16,
            88,
            8,
            40,
            90,
            40,
            8,
            16,
            77,
            16,
            16,
            16,
            16,
            16,
            16,
            16,
            16,
            16,
            16,
            16,
            16,
            16,
            16,
            16,
            16,
            16,
            16,
            16,
            16,
            16,
            16,
            16,
            16,
            16,
            16,
            16,
            16,
            16,
            16,
            16,
            16,
            16,
            16,
            16,
            16,
            16,
            16,
            16,
            16,
            16,
            16,
            16,
            16,
            16,
            16,
            16,
            16,
            8,
            16,
            16,
            16,
            16,
            16,
            16,
            16,
            16,
            16,
            16,
            5,
            6,
            5,
            6,
            20,
            0,
            16,
            16,
            16,
            16,
            16,
            16,
            16,
            16,
            16,
            16,
            16,
            16,
            16,
            6,
            5,
            6,
            4,
            36,
            16,
            16,
            16,
            16,
            28,
            91,
            16,
            1,
            16,
            92,
            13,
            35,
            35,
            16,
            6,
            6,
            16,
            16,
            16,
            16,
            16,
            16,
            16,
            21,
            8,
            93,
            0,
            93,
            8,
            93,
            8,
            94,
            16,
            3,
            16,
            16,
            16,
            16,
            16,
            16,
            16,
            16,
            28,
            95,
            16,
            41,
            16,
            95,
            16,
            95,
            16,
            16,
            16,
            16,
            16,
            16,
            16,
            16,
            16,
            16,
            16,
            28,
            95,
            16,
            16,
            16,
            95,
            16,
            95,
            16,
            16,
            16,
            16,
            16,
            16,
            16,
            16,
            16,
            16,
            16,
            28,
            95,
            16,
            16,
            16,
            95,
            16,
            95,
            16,
            16,
            16,
            16,
            16,
            16,
            16,
            16,
            16,
            16,
            16,
            13,
            8,
            93,
            93,
            93,
            8,
            93,
            8,
            96,
            16,
            16,
            16,
            16,
            16,
            16,
            16,
            16,
            16,
            16,
            28,
            95,
            16,
            97,
            16,
            95,
            98,
            65,
            65,
            16,
            16,
            16,
            16,
            16,
            16,
            16,
            16,
            16,
            16,
            28,
            95,
            16,
            97,
            16,
            95,
            25,
            99,
            16,
            16,
            16,
            16,
            16,
            16,
            16,
            16,
            16,
            16,
            16,
            100,
            95,
            16,
            97,
            16,
            95,
            14,
            99,
            16,
            16,
            16,
            16,
            16,
            16,
            101,
            16,
            16,
            16,
            16,
            13,
            8,
            93,
            93,
            93,
            8,
            100,
            7,
            16,
            16,
            16,
            16,
            16,
            102,
            103,
            16,
            16,
            16,
            16,
            28,
            91,
            16,
            16,
            16,
            92,
            27,
            16,
            16,
            16,
            16,
            16,
            102,
            104,
            16,
            104,
            16,
            16,
            16,
            16,
            16,
            16,
            16,
            16,
            16,
            16,
            16,
            16,
            16,
            16,
            102,
            104,
            105,
            106,
            105,
            104,
            16,
            8,
            16,
            16,
            16,
            16,
            16,
            16,
            16,
            16,
            16,
            16,
            16,
            16,
            23,
            16,
            16,
            16,
            16,
            16,
            16,
            16,
            16,
            16,
            16,
            16,
            16,
            16,
            16,
            16,
            16,
            16,
            30,
            16,
            16,
            16,
            16,
            16,
            16,
            16,
            16,
            100,
            91,
            0,
            92,
            27,
            16,
            16,
            16,
            16,
            16,
            16,
            16,
            16,
            16,
            16,
            16,
            16,
            16,
            16,
            28,
            107,
            1,
            108,
            109,
            13,
            13,
            35,
            16,
            16,
            16,
            16,
            16,
            16,
            16,
            16,
            16,
            16,
            16,
            28,
            110,
            90,
            90,
            90,
            90,
            63,
            94,
            16,
            16,
            16,
            16,
            16,
            16,
            16,
            16,
            16,
            16,
            16,
            13,
            87,
            111,
            85,
            8,
            111,
            8,
            89,
            16,
            16,
            16,
            16,
            16,
            16,
            16,
            16,
            16,
            16,
            16,
            14,
            110,
            111,
            112,
            112,
            112,
            63,
            96,
            16,
            16,
            16,
            16,
            16,
            16,
            16,
            16,
            16,
            16,
            16,
            28,
            87,
            8,
            13,
            13,
            65,
            13,
            65,
            16,
            16,
            16,
            16,
            16,
            16,
            16,
            16,
            16,
            16,
            16,
            28,
            87,
            111,
            85,
            21,
            16,
            16,
            16,
            16,
            16,
            16,
            16,
            16,
            16,
            16,
            16,
            16,
            16,
            16,
            14,
            87,
            111,
            85,
            27,
            16,
            16,
            16,
            16,
            16,
            16,
            16,
            16,
            16,
            16,
            16,
            16,
            16,
            16,
            28,
            110,
            111,
            85,
            13,
            16,
            16,
            16,
            16,
            16,
            16,
            16,
            16,
            16,
            16,
            16,
            16,
            16,
            16,
            13,
            63,
            8,
            63,
            13,
            16,
            16,
            16,
            16,
            16,
            16,
            16,
            102,
            16,
            16,
            16,
            16,
            16,
            16,
            28,
            91,
            32,
            92,
            27,
            16,
            16,
            16,
            16,
            16,
            16,
            16,
            104,
            105,
            16,
            104,
            105,
            106,
            16,
            16,
            16,
            16,
            16,
            16,
            16,
            16,
            16,
            16,
            16,
            102,
            104,
            105,
            106,
            105,
            105,
            106,
            8,
            106,
            16,
            16,
            16,
            16,
            104,
            16,
            104,
            102,
            104,
            16,
            16,
            53,
            16,
            16,
            16,
            16,
            16,
            16,
            16,
            16,
            16,
            95,
            16,
            16,
            16,
            16,
            16,
            16,
            16,
            16,
            16,
            16,
            16,
            16,
            16,
            16,
            16,
            16,
            16,
            28,
            95,
            27,
            16,
            16,
            16,
            16,
            16,
            16,
            16,
            16,
            16,
            16,
            16,
            16,
            16,
            16,
            16,
            16,
            13,
            0,
            100,
            16,
            16,
            16,
            16,
            16,
            16,
            16,
            16,
            16,
            16,
            16,
            16,
            16,
            16,
            16,
            16,
            28,
            95,
            35,
            35,
            100,
            100,
            35,
            16,
            16,
            16,
            16,
            16,
            16,
            16,
            16,
            16,
            16,
            16,
            16,
            28,
            95,
            93,
            93,
            93,
            93,
            93,
            93,
            16,
            16,
            16,
            16,
            16,
            16,
            16,
            16,
            16,
            16,
            16,
            14,
            95,
            98,
            65,
            65,
            65,
            13,
            16,
            16,
            16,
            16,
            16,
            16,
            16,
            16,
            16,
            16,
            16,
            16,
            100,
            95,
            13,
            16,
            16,
            16,
            16,
            16,
            16,
            16,
            16,
            16,
            16,
            16,
            16,
            16,
            16,
            16,
            16,
            13,
            95,
            13,
            16,
            16,
            16,
            16,
            16,
            16,
            16,
            16,
            16,
            16,
            16,
            16,
            16,
            16,
            16,
            16,
            28,
            95,
            14,
            16,
            16,
            16,
            16,
            16,
            16,
            16,
            16,
            16,
            16,
            16,
            16,
            16,
            16,
            16,
            16,
            13,
            95,
            27,
            16,
            16,
            16,
            16,
            16,
            16,
            16,
            16,
            16,
            16,
            16,
            16,
            16,
            16,
            16,
            16,
            28,
            95,
            27,
            16,
            16,
            16,
            16,
            16,
            16,
            16,
            16,
            16,
            16,
            16,
            16,
            16,
            16,
            16,
            16,
            28,
            95,
            27,
            16,
            16,
            16,
            16,
            16,
            16,
            16,
            16,
            104,
            105,
            104,
            16,
            105,
            16,
            16,
            16,
            16,
            95,
            16,
            16,
            16,
            16,
            16,
            16,
            16,
            16,
            104,
            105,
            106,
            105,
            16,
            106,
            8,
            106,
            16,
            16,
            113,
            16,
            16,
            16,
            16,
            16,
            16,
            16,
            16,
            16,
            16,
            16,
            16,
            16,
            16,
            16,
            16,
            16,
            16,
            96,
            16,
            16,
            16,
            16,
            16,
            16,
            16,
            16,
            16,
            16,
            16,
            16,
            16,
            16,
            16,
            16,
            16,
            16,
            7,
            16,
            16,
            16,
            16,
            16,
            16,
            16,
            16,
            16,
            16,
            16,
            16,
            16,
            16,
            16,
            16,
            16,
            16,
            1,
            16,
            16,
            16,
            16,
            16,
            16,
            16,
            16,
            16,
            16,
            16,
            16,
            16,
            16,
            16,
            16,
            16,
            16,
            7,
            16,
            16,
            16,
            16,
            16,
            16,
            16,
            16,
            16,
            16,
            16,
            16,
            16,
            16,
            16,
            16,
            16,
            16,
            25,
            7,
            25,
            7,
            25,
            7,
            91,
            16,
            16,
            16,
            16,
            16,
            16,
            16,
            16,
            16,
            16,
            16,
            16,
            7,
            16,
            16,
            16,
            16,
            16,
            16,
            16,
            16,
            16,
            16,
            16,
            16,
            16,
            16,
            16,
            16,
            16,
            16,
            100,
            16,
            16,
            16,
            16,
            16,
            16,
            16,
            16,
            16,
            16,
            16,
            16,
            16,
            16,
            16,
            16,
            16,
            16,
            7,
            16,
            16,
            16,
            16,
            16,
            16,
            16,
            16,
            16,
            16,
            16,
            16,
            16,
            16,
            16,
            16,
            16,
            16,
            13,
            16,
            16,
            16,
            16,
            16,
            16,
            16,
            16,
            16,
            16,
            16,
            16,
            16,
            16,
            16,
            16,
            16,
            16,
            7,
            16,
            16,
            16,
            16,
            16,
            16,
            16,
            16,
            16,
            16,
            16,
            16,
            16,
            16,
            16,
            16,
            16,
            16,
            13,
            16,
            16,
            16,
            16,
            16,
            16,
            16,
            16,
            16,
            16,
            16,
            16,
            16,
            16,
            16,
            16,
            16,
            16,
            7,
            16,
            16,
            16,
            16,
            16,
            16,
            16,
            16,
            16,
            16,
            105,
            16,
            16,
            105,
            106,
            16,
            16,
            16,
            94,
            16,
            16,
            16,
            16,
            16,
            16,
            16,
            16,
            104,
            105,
            106,
            105,
            105,
            106,
            8,
            106,
            16,
            16,
            16,
            16,
            16,
            16,
            16,
            16,
            16,
            16,
            16,
            16,
            16,
            16,
            16,
            16,
            16,
            16,
            16,
            16,
            16,
            16,
            16,
            16,
            16,
            16,
            16,
            16,
            105,
            16,
            16,
            16,
            16,
            16,
            16,
            16,
            16,
            16,
            16,
            16,
            16,
            16,
            16,
            16,
            16,
            16,
            16,
            106,
            105,
            16,
            16,
            16,
            16,
            16,
            16,
            16,
            16,
            16,
            16,
            0,
            16,
            16,
            16,
            16,
            16,
            16,
            105,
            16,
            16,
            16,
            16,
            16,
            16,
            16,
            16,
            16,
            16,
            16,
            16,
            16,
            16,
            16,
            16,
            16,
            16,
            16,
            16,
            16,
            16,
            16,
            16,
            16,
            16,
            16,
            16,
            16,
            16,
            16,
            16,
            16,
            16,
            16,
            16,
            16,
            16,
            16,
            16,
            16,
            16,
            16,
            16,
            16,
            16,
            16,
            16,
            16,
            16,
            16,
            16,
            16,
            16,
            16,
            16,
            16,
            16,
            16,
            16,
            16,
            16,
            16,
            16,
            16,
            16,
            16,
            16,
            16,
            16,
            16,
            16,
            16,
            16,
            16,
            16,
            16,
            16,
            16,
            16,
            16,
            16,
            16,
            16,
            16,
            16,
            16,
            16,
            16,
            16,
            16,
            16,
            16,
            16,
            16,
            16,
            16,
            16,
            16,
            16,
            16,
            16,
            16,
            16,
            16,
            16,
            16,
            16,
            16,
            16,
            16,
            16,
            16,
            16,
            16,
            16,
            16,
            16,
            16,
            16,
            16,
            16,
            16,
            16,
            16,
            16,
            16,
            16,
            16,
            16,
            16,
            16,
            16,
            16,
            16,
            16,
            16,
            16,
            16,
            16,
            16,
            16,
            16,
            16,
            16,
            16,
            16,
            16,
            16,
            16,
            16,
            16,
            16,
            16,
            16,
            16,
            16,
            16,
            16,
            16,
            16,
            16,
            16,
            16,
            16,
            16,
            16,
            16,
            16,
            16,
            16,
            16,
            16,
            16,
            16,
            16,
            16,
            16,
            106,
            16,
            16,
            16,
            16,
            16,
            16,
            16,
            16,
            16,
            16,
            16,
            16,
            16,
            105,
            106,
            105,
            16,
            106,
            114,
            106,
            16,
            16,
            16,
            16,
            16,
            16,
            16,
            16,
            16,
            16,
            16,
            16,
            16,
            16,
            16,
            16,
            16,
            16,
            16,
            16,
            16,
            16,
            16,
            16,
            16,
            16,
            16,
            16,
            105,
            16,
            16,
            16,
            16,
            16,
            16,
            16,
            16,
            16,
            16,
            16,
            16,
            16,
            16,
            16,
            16,
            16,
            16,
            106,
            16,
            16,
            16,
            16,
            16,
            16,
            16,
            16,
            16,
            16,
            16,
            1,
            16,
            16,
            16,
            16,
            16,
            16,
            105,
            16,
            16,
            16,
            16,
            16,
            16,
            16,
            16,
            16,
            16,
            16,
            16,
            16,
            16,
            16,
            16,
            16,
            16,
            16,
            16,
            16,
            16,
            16,
            16,
            16,
            16,
            16,
            16,
            16,
            16,
            16,
            16,
            16,
            16,
            16,
            16,
            16,
            16,
            16,
            16,
            16,
            16,
            16,
            16,
            16,
            16,
            16,
            16,
            16,
            16,
            16,
            16,
            16,
            16,
            16,
            16,
            16,
            16,
            16,
            16,
            16,
            16,
            16,
            16,
            16,
            16,
            16,
            16,
            16,
            16,
            16,
            16,
            16,
            16,
            16,
            16,
            16,
            16,
            16,
            16,
            16,
            16,
            16,
            16,
            16,
            16,
            16,
            16,
            16,
            16,
            16,
            16,
            16,
            16,
            16,
            16,
            16,
            16,
            16,
            16,
            16,
            16,
            16,
            16,
            16,
            16,
            16,
            16,
            16,
            16,
            16,
            16,
            16,
            16,
            16,
            16,
            16,
            16,
            16,
            16,
            16,
            16,
            16,
            16,
            16,
            16,
            16,
            16,
            16,
            16,
            16,
            16,
            16,
            16,
            16,
            16,
            16,
            16,
            16,
            16,
            16,
            16,
            16,
            16,
            16,
            16,
            16,
            16,
            16,
            16,
            16,
            16,
            16,
            16,
            16,
            16,
            16,
            16,
            16,
            16,
            16,
            16,
            16,
            16,
            16,
            16,
            16,
            16,
            16,
            16,
            16,
            16,
            16,
            16,
            105,
            16,
            16,
            16,
            105,
            16,
            16,
            16,
            16,
            16,
            16,
            16,
            16,
            16,
            16,
            16,
            16,
            16,
            105,
            106,
            105,
            16,
            105,
            106,
            105,
            16,
            16,
            16,
            16,
            16,
            16,
            16,
            16,
            16,
            16,
            16,
            16,
            16,
            16,
            16,
            16,
            16,
            16,
            16,
            16,
            16,
            16,
            16,
            16,
            16,
            16,
            16,
            16,
            105,
            16,
            16,
            16,
            16,
            16,
            16,
            16,
            16,
            16,
            16,
            16,
            16,
            16,
            16,
            16,
            16,
            16,
            16,
            106,
            105,
            16,
            16,
            16,
            16,
            16,
            16,
            16,
            16,
            16,
            16,
            2,
            16,
            16,
            16,
            16,
            16,
            16,
            105,
            16,
            16,
            16,
            16,
            16,
            16,
            16,
            16,
            16,
            16,
            16,
            16,
            16,
            16,
            16,
            16,
            16,
            16,
            16,
            16,
            16,
            16,
            16,
            16,
            16,
            16,
            16,
            16,
            16,
            16,
            16,
            16,
            16,
            16,
            16,
            16,
            16,
            16,
            16,
            16,
            16,
            16,
            16,
            16,
            16,
            16,
            16,
            16,
            16,
            16,
            16,
            16,
            16,
            16,
            16,
            16,
            16,
            16,
            16,
            16,
            16,
            16,
            16,
            16,
            16,
            16,
            16,
            16,
            16,
            16,
            16,
            16,
            16,
            16,
            16,
            16,
            16,
            16,
            16,
            16,
            16,
            16,
            16,
            16,
            16,
            16,
            16,
            16,
            16,
            16,
            16,
            16,
            16,
            16,
            16,
            16,
            16,
            16,
            16,
            16,
            16,
            16,
            16,
            16,
            16,
            16,
            16,
            16,
            16,
            16,
            16,
            16,
            16,
            16,
            16,
            16,
            16,
            16,
            16,
            16,
            16,
            16,
            16,
            16,
            16,
            16,
            16,
            16,
            16,
            16,
            16,
            16,
            16,
            16,
            16,
            16,
            16,
            16,
            16,
            16,
            16,
            16,
            16,
            16,
            16,
            16,
            16,
            16,
            16,
            16,
            16,
            16,
            16,
            16,
            16,
            16,
            16,
            16,
            16,
            16,
            16,
            16,
            16,
            16,
            16,
            16,
            16,
            16,
            16,
            16,
            16,
            16,
            16,
            16,
            16,
            16,
            16,
            16,
            16,
            16,
            16,
            16,
            16,
            16,
            16,
            16,
            16,
            16,
            16,
            16,
            16,
            16,
            104,
            105,
            104,
            16,
            16,
            105,
            16,
            16,
            16,
            16,
            16,
            16,
            16,
            16,
            16,
            16,
            16,
            16,
            16,
            16,
            16,
            16,
            16,
            16,
            16,
            16,
            16,
            16,
            16,
            16,
            16,
            16,
            16,
            16,
            16,
            16,
            16,
            16,
            16,
            16,
            16,
            16,
            16,
            16,
            16,
            16,
            16,
            115,
            16,
            16,
            16,
            16,
            16,
            16,
            106,
            16,
            16,
            16,
            16,
            16,
            16,
            16,
            16,
            16,
            16,
            116,
            117,
            56,
            16,
            16,
            16,
            16,
            16,
            16,
            16,
            16,
            16,
            16,
            16,
            16,
            16,
            16,
            16,
            16,
            16,
            118,
            16,
            16,
            16,
            16,
            16,
            16,
            16,
            16,
            16,
            16,
            16,
            16,
            16,
            16,
            16,
            16,
            16,
            16,
            16,
            16,
            16,
            16,
            16,
            16,
            16,
            16,
            16,
            16,
            16,
            16,
            16,
            16,
            16,
            16,
            16,
            16,
            16,
            16,
            16,
            16,
            16,
            16,
            16,
            16,
            16,
            16,
            16,
            16,
            16,
            16,
            16,
            16,
            16,
            16,
            16,
            16,
            16,
            16,
            16,
            16,
            16,
            16,
            16,
            16,
            16,
            16,
            16,
            16,
            16,
            16,
            16,
            16,
            16,
            16,
            16,
            16,
            16,
            16,
            16,
            16,
            16,
            16,
            16,
            16,
            16,
            16,
            16,
            16,
            16,
            16,
            16,
            16,
            16,
            16,
            16,
            16,
            16,
            16,
            16,
            16,
            16,
            16,
            16,
            16,
            16,
            16,
            16,
            16,
            16,
            16,
            16,
            16,
            16,
            16,
            16,
            16,
            16,
            16,
            16,
            16,
            16,
            16,
            16,
            16,
            16,
            16,
            16,
            16,
            16,
            16,
            16,
            16,
            16,
            16,
            16,
            16,
            16,
            16,
            16,
            16,
            16,
            16,
            16,
            16,
            16,
            16,
            16,
            16,
            16,
            16,
            16,
            16,
            16,
            16,
            16,
            16,
            16,
            16,
            16,
            16,
            16,
            16,
            16,
            16,
            16,
            16,
            16,
            16,
            16,
            16,
            16,
            16,
            16,
            16,
            16,
            16,
            16,
            16,
            16,
            16,
            16,
            104,
            16,
            16,
            16,
            104,
            16,
            16,
            16,
            16,
            16,
            16,
            16,
            16,
            16,
            16,
            16,
            16,
            16,
            16,
            16,
            16,
            16,
            16,
            16,
            16,
            16,
            16,
            16,
            16,
            16,
            16,
            16,
            16,
            16,
            16,
            16,
            16,
            16,
            16,
            16,
            16,
            16,
            16,
            16,
            16,
            16,
            16,
            16,
            16,
            16,
            16,
            16,
            16,
            105,
            16,
            16,
            16,
            16,
            16,
            16,
            16,
            16,
            16,
            16,
            16,
            16,
            16,
            16,
            16,
            16,
            16,
            16,
            16,
            16,
            16,
            16,
            16,
            16,
            16,
            16,
            16,
            16,
            16,
            16,
            16,
            16,
            16,
            16,
            16,
            16,
            16,
            16,
            16,
            16,
            16,
            16,
            16,
            16,
            16,
            16,
            16,
            16,
            16,
            16,
            16,
            16,
            16,
            16,
            16,
            16,
            16,
            16,
            16,
            16,
            16,
            16,
            16,
            16,
            16,
            16,
            16,
            16,
            16,
            16,
            16,
            16,
            16,
            16,
            16,
            16,
            16,
            16,
            16,
            16,
            16,
            16,
            16,
            16,
            16,
            16,
            16,
            16,
            16,
            16,
            16,
            16,
            16,
            16,
            16,
            16,
            16,
            16,
            16,
            16,
            16,
            16,
            16,
            16,
            16,
            16,
            16,
            16,
            16,
            16,
            16,
            16,
            16,
            16,
            16,
            16,
            16,
            16,
            16,
            16,
            16,
            16,
            16,
            16,
            16,
            16,
            16,
            16,
            16,
            16,
            16,
            16,
            16,
            16,
            16,
            16,
            16,
            16,
            16,
            16,
            16,
            16,
            16,
            16,
            16,
            16,
            16,
            16,
            16,
            16,
            16,
            16,
            16,
            16,
            16,
            16,
            16,
            16,
            16,
            16,
            16,
            16,
            16,
            16,
            16,
            16,
            16,
            16,
            16,
            16,
            16,
            16,
            16,
            16,
            16,
            16,
            16,
            16,
            16,
            16,
            16,
            16,
            16,
            16,
            16,
            16,
            16,
            16,
            16,
            16,
            16,
            16,
            16,
            16,
            16,
            16,
            16,
            16,
            16,
            16,
            16,
            16,
            16,
            16,
            16,
            16,
            16,
            16,
            16,
            16,
            16,
            16,
            102,
            16,
            16,
            16,
            16,
            16,
            16,
            16,
            16,
            16,
            16,
            16,
            16,
            16,
            16,
            16,
            16,
            16,
            16,
            16,
            16,
            16,
            16,
            16,
            16,
            16,
            16,
            16,
            16,
            16,
            16,
            16,
            16,
            16,
            16,
            16,
            16,
            16,
            16,
            16,
            16,
            16,
            16,
            16,
            16,
            16,
            16,
            16,
            16,
            16,
            16,
            16,
            16,
            16,
            16,
            16,
            16,
            16,
            16,
            16,
            16,
            16,
            16,
            16,
            16,
            16,
            16,
            16,
            16,
            16,
            16,
            16,
            16,
            16,
            16,
            16,
            16,
            16,
            16,
            16,
            16,
            16,
            16,
            16,
            16,
            16,
            16,
            16,
            16,
            16,
            16,
            16,
            16,
            16,
            16,
            16,
            16,
            16,
            16,
            16,
            16,
            16,
            16,
            16,
            16,
            16,
            16,
            16,
            16,
            16,
            16,
            16,
            16,
            16,
            16,
            16,
            16,
            16,
            16,
            16,
            16,
            16,
            16,
            16,
            16,
            16,
            16,
            16,
            16,
            16,
            16,
            16,
            16,
            16,
            16,
            16,
            16,
            16,
            16,
            16,
            16,
            16,
            16,
            16,
            16,
            16,
            16,
            16,
            16,
            16,
            16,
            16,
            16,
            16,
            16,
            16,
            16,
            16,
            16,
            16,
            16,
            16,
            16,
            16,
            16,
            16,
            16,
            16,
            16,
            16,
            16,
            16,
            16,
            16,
            16,
            16,
            16,
            16,
            16,
            16,
            16,
            16,
            16,
            16,
            16,
            16,
            16,
            16,
            16,
            16,
            16,
            16,
            16,
            16,
            16,
            16,
            16,
            16,
            16,
            16,
            16,
            16,
            16,
            16,
            16,
            16,
            16,
            16,
            16,
            16,
            16,
            16,
            16,
            16,
            16,
            16,
            16,
            16,
            16,
            16,
            16,
            16,
            16,
            16,
            16,
            16,
            16,
            16,
            16,
            16,
            16,
            16,
            16,
            16,
            16,
            16,
            16,
            16,
            16,
            16,
            16,
            16,
            16,
            16,
            16,
            16,
            16,
            16,
            16,
            16,
            16,
            16,
            16,
            16,
            16,
            16,
            16,
            16,
            16,
            16,
            16,
            16,
            16,
            16,
            16,
            16,
            16,
            16,
            16,
            16,
            16,
            16,
            16,
            16,
            16,
            16,
            16,
            16,
            16,
            16,
            16,
            16,
            16,
            16,
            16,
            16,
            16,
            16,
            16,
            16,
            16,
            16,
            16,
            16,
            16,
            16,
            16,
            16,
            16,
            16,
            16,
            16,
            16,
            16,
            16,
            16,
            16,
            16,
            16,
            16,
            16,
            16,
            16,
            16,
            16,
            16,
            16,
            16,
            16,
            16,
            16,
            16,
            16,
            16,
            16,
            16,
            16,
            16,
            16,
            16,
            16,
            16,
            16,
            16,
            16,
            16,
            16,
            16,
            16,
            16,
            16,
            16,
            16,
            16,
            16,
            16,
            16,
            16,
            16,
            16,
            16,
            16,
            16,
            16,
            16,
            16,
            16,
            16,
            16,
            16,
            16,
            16,
            16,
            16,
            16,
            16,
            16,
            16,
            16,
            16,
            16,
            16,
            16,
            16,
            16,
            16,
            16,
            16,
            16,
            16,
            16,
            16,
            16,
            16,
            16,
            16,
            16,
            16,
            16,
            16,
            16,
            16,
            16,
            16,
            16,
            16,
            16,
            16,
            16,
            16,
            16,
            16,
            16,
            16,
            16,
            16,
            16,
            16,
            16,
            16,
            16,
            16,
            16,
            16,
            16,
            16,
            16,
            16,
            16,
            16,
            16,
            16,
            16,
            16,
            16,
            16,
            16,
            16,
            16,
            16,
            16,
            16,
            16,
            16,
            16,
            16,
            16,
            16,
            16,
            16,
            16,
            16,
            16,
            16,
            16,
            16,
            16,
            16,
            16,
            16,
            16,
            16,
            16,
            16,
            16,
            16,
            16,
            16,
            16,
            16,
            16,
            16,
            16,
            16,
            16,
            16,
            16,
            16,
            16,
            16,
            16,
            16,
            16,
            16,
            16,
            16,
            16,
            16,
            16,
            16,
            16,
            16,
            16,
            16,
            16,
            16,
            16,
            16,
            16,
            16,
            16,
            16,
            16,
            16,
            16,
            16,
            16,
            16,
            16,
            16,
            16,
            16,
            16,
            16,
            16,
            16,
            16,
            16,
            16,
            16,
            16,
            16,
            16,
            16,
            16,
            16,
            16,
            16,
            16,
            16,
            16,
            16,
            16,
            16,
            16,
            16,
            16,
            16,
            16,
            16,
            16,
            16,
            16,
            16,
            16,
            16,
            16,
            16,
            16,
            16,
            16,
            16,
            16,
            16,
            16,
            16,
            16,
            16,
            16,
            16,
            16,
            16,
            16,
            16,
            16,
            16,
            16,
            16,
            16,
            16,
            16,
            16,
            16,
            16,
            16,
            16,
            16,
            16,
            16,
            16,
            16,
            16,
            16,
            16,
            16,
            16,
            16,
            16,
            16,
            16,
            16,
            16,
            16,
            16,
            16,
            16,
            16,
            16,
            16,
            16,
            16,
            16,
            16,
            16,
            16,
            16,
            16,
            16,
            16,
            16,
            16,
            16,
            16,
            16,
            16,
            16,
            16,
            16,
            16,
            16,
            16,
            16,
            16,
            16,
            16,
            16,
            16,
            16,
            16,
            16,
            16,
            16,
            16,
            16,
            16,
            16,
            16,
            16,
            16,
            16,
            16,
            16,
            16,
            16,
            16,
            16,
            16,
            16,
            16,
            16,
            16,
            16,
            16,
            16,
            16,
            16,
            16,
            16,
            16,
            16,
            16,
            16,
            16,
            16,
            16,
            16,
            16,
            16,
            16,
            16,
            16,
            16,
            16,
            16,
            16,
            16,
            16,
            16,
            16,
            16,
            16,
            16,
            16,
            16,
            16,
            16,
            16,
            16,
            16,
            16,
            16,
            16,
            16,
            16,
            16,
            16,
            16,
            16,
            16,
            16,
            16,
            16,
            16,
            16,
            16,
            16,
            16,
            16,
            16,
            16,
            16,
            16,
            16,
            16,
            16,
            16,
            16,
            16,
            16,
            16,
            16,
            16,
            16,
            16,
            16,
            16,
            16,
            16,
            16,
            16,
            16,
            16,
            16,
            16,
            16,
            16,
            16,
            16,
            16,
            16,
            16,
            16,
            16,
            16,
            16,
            16,
            16,
            16,
            16,
            16,
            16,
            16,
            16,
            16,
            16,
            16,
            16,
            16,
            16,
            16,
            16,
            16,
            16,
            16,
            16,
            16,
            16,
            16,
            16,
            16,
            16,
            16,
            16,
            16,
            16,
            16,
            16,
            16,
            16,
            16,
            16,
            16,
            16,
            16,
            16,
            16,
            16,
            16,
            16,
            16,
            16,
            16,
            16,
            16,
            16,
            16,
            16,
            16,
            16,
            16,
            16,
            16,
            16,
            16,
            16,
            16,
            16,
            16,
            16,
            16,
            16,
            16,
            16,
            16,
            16,
            16,
            16,
            16,
            16,
            16,
            16,
            16,
            16
        ]
    })
}